tekcify_auth/__init__.py
tekcify_auth-0.1.0.dist-info/licenses/LICENSE
tekcify_auth-0.1.0.dist-info/METADATA
tekcify_auth-0.1.0.dist-info/WHEEL
tekcify_auth-0.1.0.dist-info/top_level.txt
tekcify_auth-0.1.0.dist-info/RECORD
