Metadata-Version: 2.4
Name: tekcify-auth
Version: 0.1.0
Summary: Authentication library for Tekcify services
Home-page: https://github.com/tekcify/tekcify-auth-python-library
Author: Agboola Olamidipupo Favour
Author-email: dipoagboola2019@campux.io
Classifier: Programming Language :: Python :: 3
Classifier: License :: OSI Approved :: MIT License
Classifier: Operating System :: OS Independent
Requires-Python: >=3.6
License-File: LICENSE
Requires-Dist: requests>=2.25.0
Dynamic: author
Dynamic: author-email
Dynamic: classifier
Dynamic: description
Dynamic: description-content-type
Dynamic: home-page
Dynamic: license-file
Dynamic: requires-dist
Dynamic: requires-python
Dynamic: summary
